jsontoexcel/  __init__.py
jsontoexcel/SampleCode.py
jsontoexcel/jsontoexcel.py
jsontoexcel-0.6.dist-info/LICENSE
jsontoexcel-0.6.dist-info/METADATA
jsontoexcel-0.6.dist-info/WHEEL
jsontoexcel-0.6.dist-info/top_level.txt
jsontoexcel-0.6.dist-info/RECORD
