Metadata-Version: 2.1
Name: jsontoexcel
Version: 0.6
Summary: Package to convert complex json objects into excel
Home-page: https://github.com/akritianand/JsonToExcel
Author: Akriti Anand
License: UNKNOWN
Platform: UNKNOWN
Classifier: Programming Language :: Python :: 3
Classifier: License :: OSI Approved :: MIT License
Classifier: Operating System :: OS Independent
Requires-Python: >=3.6
